trustspeccli/__init__.py
trustspeccli/main.py
trustspeccli-0.1.64.dist-info/METADATA
trustspeccli-0.1.64.dist-info/WHEEL
trustspeccli-0.1.64.dist-info/entry_points.txt
trustspeccli-0.1.64.dist-info/RECORD
